sstool_general/__init__.py
sstool_general/doc.py
sstool_general/openapi.py
sstool_general/options.py
sstool_general/serializer.py
sstool_general/swagger.py
sstool_general/utils.py
sstool_general/validators.py
sstool_general-0.0.4.dist-info/LICENSE
sstool_general-0.0.4.dist-info/METADATA
sstool_general-0.0.4.dist-info/WHEEL
sstool_general-0.0.4.dist-info/top_level.txt
sstool_general-0.0.4.dist-info/RECORD
